jcs_mediagraphic/__init__.py
jcs_mediagraphic/pdf.py
jcs_mediagraphic/windows.py
jcs_mediagraphic-0.1.3.dist-info/METADATA
jcs_mediagraphic-0.1.3.dist-info/WHEEL
jcs_mediagraphic-0.1.3.dist-info/top_level.txt
jcs_mediagraphic-0.1.3.dist-info/RECORD
