Metadata-Version: 2.1
Name: jcs-mediagraphic
Version: 0.1.3
Summary: Python library for MediaGraphic Group usages
Author: Jean Chabanol-Seroude
License: BSD
Requires-Dist: pip
Requires-Dist: fpdf2
Requires-Dist: Pillow
